sitecustomize.py
tbhandler/__init__.py
tbhandler/config.py
tbhandler/exc_info.py
tbhandler/extension.py
tbhandler/monkeypatch.py
tbhandler/opener.py
tbhandler/path.py
tbhandler/sitecustomize_remover.py
tbhandler/tbhandler.py
tests/test_error_handling.py
tests/test_install.py
tbhandler-0.1.3.dist-info/LICENSE
tbhandler-0.1.3.dist-info/METADATA
tbhandler-0.1.3.dist-info/WHEEL
tbhandler-0.1.3.dist-info/entry_points.txt
tbhandler-0.1.3.dist-info/top_level.txt
tbhandler-0.1.3.dist-info/RECORD
