Metadata-Version: 2.1
Name: tbhandler
Version: 0.1.3
Summary: Automated detailed traceback visualization
Author-email: Quinten Roets <qdr2104@columbia.edu>
License: MIT
Project-URL: Source Code, https://github.com/quintenroets/tbhandler
Requires-Python: >=3.10
License-File: LICENSE
Requires-Dist: powercli
Requires-Dist: rich
Requires-Dist: superpathlib
Provides-Extra: dev
Requires-Dist: pre-commit ; extra == 'dev'
Provides-Extra: test
Requires-Dist: pytest ; extra == 'test'
